calcalc/CalCalc.py
calcalc/__init__.py
calcalc/setup.py
calcalc/tests/__init__.py
calcalc/tests/test_calculate.py
CalcalcTT-0.0.4.dist-info/METADATA
CalcalcTT-0.0.4.dist-info/WHEEL
CalcalcTT-0.0.4.dist-info/top_level.txt
CalcalcTT-0.0.4.dist-info/RECORD
